zetsubou/__init__.py
zetsubou/cli.py
zetsubou/client.py
zetsubou/exceptions.py
zetsubou/models.py
zetsubou/services/__init__.py
zetsubou/services/account.py
zetsubou/services/chat.py
zetsubou/services/graphql.py
zetsubou/services/jobs.py
zetsubou/services/nft.py
zetsubou/services/tools.py
zetsubou/services/vfs.py
zetsubou/services/webhooks.py
zetsubou_sdk-1.1.0.dist-info/METADATA
zetsubou_sdk-1.1.0.dist-info/WHEEL
zetsubou_sdk-1.1.0.dist-info/entry_points.txt
zetsubou_sdk-1.1.0.dist-info/top_level.txt
zetsubou_sdk-1.1.0.dist-info/RECORD
